AUTHORS
LICENSE
MANIFEST.in
README.rst
requirements.txt
setup.py
django_mediasync.egg-info/PKG-INFO
django_mediasync.egg-info/SOURCES.txt
django_mediasync.egg-info/dependency_links.txt
django_mediasync.egg-info/requires.txt
django_mediasync.egg-info/top_level.txt
mediasync/__init__.py
mediasync/conf.py
mediasync/models.py
mediasync/signals.py
mediasync/urls.py
mediasync/views.py
mediasync/backends/__init__.py
mediasync/backends/cloudfiles.py
mediasync/backends/dummy.py
mediasync/backends/s3.py
mediasync/management/__init__.py
mediasync/management/commands/__init__.py
mediasync/management/commands/syncmedia.py
mediasync/processors/__init__.py
mediasync/processors/closurecompiler.py
mediasync/processors/slim.py
mediasync/processors/yuicompressor.py
mediasync/templatetags/__init__.py
mediasync/templatetags/media.py
mediasync/tests/__init__.py
mediasync/tests/models.py
mediasync/tests/settings.py
mediasync/tests/tests.py
mediasync/tests/media/_test/joined.css
mediasync/tests/media/_test/joined.js
mediasync/tests/media/css/1.css
mediasync/tests/media/css/2.css
mediasync/tests/media/css/3.scss
mediasync/tests/media/img/black.png
mediasync/tests/media/js/1.js
mediasync/tests/media/js/2.js