Metadata-Version: 1.0
Name: django-mediasync
Version: 2.2.0
Summary: Django static media development and distribution tools
Home-page: http://github.com/sunlightlabs/django-mediasync/
Author: Jeremy Carbaugh
Author-email: jcarbaugh@sunlightfoundation.com
License: BSD License
Platform: any
Classifier: Development Status :: 4 - Beta
Classifier: Intended Audience :: Developers
Classifier: License :: OSI Approved :: BSD License
Classifier: Natural Language :: English
Classifier: Operating System :: OS Independent
Classifier: Programming Language :: Python
Classifier: Environment :: Web Environment
